d_fetch/__init__.py
d_fetch/main.py
d_fetch/messages.py
d_fetch/py.typed
d_fetch/engine/__init__.py
d_fetch/engine/base.py
d_fetch/engine/regular_downloader.py
d_fetch/engine/youtube_downloader.py
d_fetch/utils/helpers.py
dfetch_cli-0.0.1.dist-info/METADATA
dfetch_cli-0.0.1.dist-info/WHEEL
dfetch_cli-0.0.1.dist-info/entry_points.txt
dfetch_cli-0.0.1.dist-info/licenses/LICENSE
dfetch_cli-0.0.1.dist-info/RECORD
