Metadata-Version: 2.4
Name: dfetch-cli
Version: 0.0.1
Summary: Fast multi-connection downloader
Author-email: Dayona <arifadayona@gmail.com>
License-File: LICENSE
Requires-Python: >=3.10
Requires-Dist: httpx
Requires-Dist: tqdm
Requires-Dist: yt-dlp>=2026.1.29
